{
  "nightly": {
    "description": "nightly",
    "hide": false,
    "last_updated": "2025-11-20T01:04:29.000Z",
    "last_updated_url": "https://github.com/engels74/qflood/actions/runs/19521680731",
    "latest": false,
    "tags": [
      "nightly",
      "nightly-5.1.4--18879148181",
      "nightly-49acb75"
    ]
  },
  "release": {
    "description": "Releases",
    "hide": false,
    "last_updated": "2025-11-20T01:04:33.000Z",
    "last_updated_url": "https://github.com/engels74/qflood/actions/runs/19521682012",
    "latest": true,
    "tags": [
      "release",
      "release-5.1.4--4.11.0",
      "release-6c8d1ae"
    ]
  }
}
