{
  "build_revision_lib1": "3",
  "build_revision_lib2": "3",
  "description": "nightly",
  "flood_version": "16838168786",
  "full_version_lib1": "release-5.1.2_v1.2.20",
  "full_version_lib2": "release-5.1.2_v2.0.11",
  "latest": false,
  "test_amd64": true,
  "test_arm64": true,
  "test_url": "http://localhost:3000",
  "upstream_digest_amd64": "sha256:46893297a3166a562fd22ab750b4e24e7f919f5261c927c0eb6327624b5ca171",
  "upstream_digest_arm64": "sha256:2e8133f450e337bd1e3046a922212c4b3a08ecad776f358807e1ce2e71c71627",
  "upstream_image": "ghcr.io/engels74/base-image",
  "upstream_tag": "alpinevpn",
  "version": "5.1.2--16838168786"
}
